Workbook

Sheet Display
E3: Rate | F3: Amount | J3: Year 1 | K3: Year 2 | L3: Year 3 | M3: Year 4 | N3: Year 5
D4: =Inputs!B5 -> OG 5th 3rd LOC I/O for 12 Months | E4: =Inputs!C5 -> 0.075 | F4: =Inputs!F13 -> 2000000 | I4: =D4 -> OG 5th 3rd LOC I/O for 12 Months | J4: ='Per Loan'!C20 -> 150000 | K4: ='Per Loan'!F20 -> 368118.62 | L4: =K4 -> 368118.62 | M4: =L4 -> 368118.62 | N4: =M4 -> 368118.62
D5: =Inputs!B6 -> RE | E5: =Inputs!C6 -> 0.068 | F5: =Inputs!E14 -> 790500 | I5: =D5 -> RE | J5: ='Per Loan'!C21 -> 72410.388 | K5: ='Per Loan'!F21 -> 72410.388 | L5: =K5 -> 72410.388 | M5: =L5 -> 72410.388 | N5: =M5 -> 72410.388
D6: =Inputs!B7 -> Seller Fin | E6: =Inputs!C7 -> 0.05 | F6: =Inputs!D7 -> 1000000 | I6: =D6 -> Seller Fin | J6: ='Per Loan'!C22 -> 226454.8 | K6: ='Per Loan'!F22 -> 226454.8 | L6: =K6 -> 226454.8 | M6: =L6 -> 226454.8 | N6: =M6 -> 226454.8
D7: =Inputs!B8 -> 5th 3rd LOC/Loan | E7: =Inputs!C8 -> 0.075 | F7: =Inputs!D8 -> 750000 | I7: =D7 -> 5th 3rd LOC/Loan | J7: ='Per Loan'!C23 -> 180341.54 | K7: ='Per Loan'!F23 -> 180341.54 | L7: =K7 -> 180341.54 | M7: =L7 -> 180341.54 | N7: =M7 -> 180341.54
I8: Annual Debt Service | J8: =SUM(J4:J7) -> 629206.73 | K8: =SUM(K4:K7) -> 847325.35 | L8: =SUM(L4:L7) -> 847325.35 | M8: =SUM(M4:M7) -> 847325.35 | N8: =SUM(N4:N7) -> 847325.35
I9: EBITDA @ 3% Growth | J9: ='Buckeye P&L'!M11*1.03 -> 1374681.3 | K9: =J9*1.03 -> 1415921.7 | L9: =K9*1.03 -> 1458399.3 | M9: =L9*1.03 -> 1502151.3 | N9: =M9*1.03 -> 1547215.9
D10: Total Purchase Price | E10: Total RE Price | F10: Operating Business Price | I10: Net Cash Flow | J10: =J9-J8 -> 745474.53 | K10: =K9-K8 -> 568596.35 | L10: =L9-L8 -> 611074 | M10: =M9-M8 -> 654825.98 | N10: =N9-N8 -> 699890.52
D11: =Inputs!D11 -> 5000000 | E11: 900000 | F11: =D11-E11 -> 4100000 | I11: ROI | J11: =J10/$F$19 -> 1.6223602 | K11: =(K10+J10)/$F$19 -> 2.8597843 | L11: =(J10+L10+K10)/$F$19 -> 4.1896515 | M11: =(J10+K10+M10+L10)/$F$19 -> 5.6147353 | N11: =(J10+K10+L10+N10+M10)/$F$19 -> 7.137892
C13: =Inputs!C13 -> OG 5th 3rd LOC | F13: =F4 -> 2000000 | I13: Monthly Debt Service | J13: =J8/12 -> 52433.894 | K13: =K8/12 -> 70610.446 | L13: =L8/12 -> 70610.446 | M13: =M8/12 -> 70610.446 | N13: =N8/12 -> 70610.446
C14: =Inputs!C14 -> RE Loan | E14: =F5 -> 790500
C15: =Inputs!C15 -> Seller Fin | F15: =F6 -> 1000000
C16: =Inputs!C16 -> 5th 3rd LOC/Loan | F16: =F7 -> 750000
D17: Cash To Closing | E17: =E11-E14 -> 109500 | F17: =F11-F13-F15-F16 -> 350000
E19: Cash To Closing | F19: =F17+E17 -> 459500
D21: Total Amount Financed | F21: =F13+E14+F15 -> 3790500
J25: =J3 -> Year 1 | K25: =K3 -> Year 2 | L25: =L3 -> Year 3 | M25: =M3 -> Year 4 | N25: =N3 -> Year 5
I26: =I9 -> EBITDA @ 3% Growth | J26: =J9 -> 1374681.3 | K26: =K9 -> 1415921.7 | L26: =L9 -> 1458399.3 | M26: =M9 -> 1502151.3 | N26: =N9 -> 1547215.9
I27: =I4 -> OG 5th 3rd LOC I/O for 12 Months | J27: =J4 -> 150000 | K27: =K4 -> 368118.62 | L27: =L4 -> 368118.62 | M27: =M4 -> 368118.62 | N27: =N4 -> 368118.62
I28: =I5 -> RE | J28: =J5 -> 72410.388 | K28: =K5 -> 72410.388 | L28: =L5 -> 72410.388 | M28: =M5 -> 72410.388 | N28: =N5 -> 72410.388
I29: =I6 -> Seller Fin | J29: =J6 -> 226454.8 | K29: =K6 -> 226454.8 | L29: =L6 -> 226454.8 | M29: =M6 -> 226454.8 | N29: =N6 -> 226454.8
I30: =I7 -> 5th 3rd LOC/Loan | J30: =J7 -> 180341.54 | K30: =K7 -> 180341.54 | L30: =L7 -> 180341.54 | M30: =M7 -> 180341.54 | N30: =N7 -> 180341.54
I31: =I8 -> Annual Debt Service | J31: =SUM(J27:J30) -> 629206.73 | K31: =SUM(K27:K30) -> 847325.35 | L31: =SUM(L27:L30) -> 847325.35 | M31: =SUM(M27:M30) -> 847325.35 | N31: =SUM(N27:N30) -> 847325.35
I32: =I10 -> Net Cash Flow | J32: =J10 -> 745474.53 | K32: =K10 -> 568596.35 | L32: =L10 -> 611074 | M32: =M10 -> 654825.98 | N32: =N10 -> 699890.52
I33: Cumulative ROI (cash-on-cash vs. cash-to-close $459,500) | J33: =J11 -> 1.6223602 | K33: =K11 -> 2.8597843 | L33: =L11 -> 4.1896515 | M33: =M11 -> 5.6147353 | N33: =N11 -> 7.137892

Sheet Per Loan
B2: =Inputs!B5 -> OG 5th 3rd LOC I/O for 12 Months | E2: =Inputs!B7 -> Seller Fin | H2: =Inputs!B6 -> RE | K2: =Inputs!B8 -> 5th 3rd LOC/Loan
B3: =E3 -> Original Principal | C3: =Inputs!D5 -> 2000000 | E3: =H3 -> Original Principal | F3: =Inputs!D7 -> 1000000 | H3: =K3 -> Original Principal | I3: =Inputs!E14 -> 790500 | K3: Original Principal | L3: =Inputs!D8 -> 750000
B4: =E4 -> Term (Years) | C4: =7 -> 7 | E4: =H4 -> Term (Years) | F4: =5 -> 5 | H4: =K4 -> Term (Years) | I4: 20 | K4: Term (Years) | L4: =5 -> 5
B5: =E5 -> Rate | C5: =Inputs!C5 -> 0.075 | E5: =H5 -> Rate | F5: =Inputs!C7 -> 0.05 | H5: =K5 -> Rate | I5: =Inputs!C6 -> 0.068 | K5: Rate | L5: =Inputs!C8 -> 0.075
B6: =E6 -> Payments per Year | C6: =F6 -> 12 | E6: =H6 -> Payments per Year | F6: =I6 -> 12 | H6: =K6 -> Payments per Year | I6: 12 | K6: Payments per Year | L6: =12 -> 12
B7: =E7 -> Monthly Payment | C7: =PMT(C$5/C$6, C$4*C$6, -C$3) -> 30676.552 | E7: =H7 -> Monthly Payment | F7: =PMT(F$5/F$6, F$4*F$6, -F$3) -> 18871.234 | H7: =K7 -> Monthly Payment | I7: =PMT(I$5/I$6, I$4*I$6, -I$3) -> 6034.199 | K7: Monthly Payment | L7: =PMT(L$5/L$6, L$4*L$6, -L$3) -> 15028.461
B8: =E8 -> Annual DS | C8: =C6*C7 -> 368118.62 | E8: =H8 -> Annual DS | F8: =F6*F7 -> 226454.8 | H8: =K8 -> Annual DS | I8: =I6*I7 -> 72410.388 | K8: Annual DS | L8: =L6*L7 -> 180341.54
B11: =B2 -> OG 5th 3rd LOC I/O for 12 Months | C11: I/O 12 Month Period
B12: =B3 -> Original Principal | C12: =C3 -> 2000000
B13: =B4 -> Term (Years)
B14: =B5 -> Rate | C14: =C5 -> 0.075
B15: =B6 -> Payments per Year | C15: =C6 -> 12
B16: =B7 -> Monthly Payment | C16: =C17/12 -> 12500
B17: =B8 -> Annual DS | C17: =C12*C14 -> 150000
B19: I/O Period Annual Debt Service | E19: Termed Out Annual Debt Service
B20: =E20 -> OG 5th 3rd LOC I/O for 12 Months | C20: =C17 -> 150000 | E20: =B2 -> OG 5th 3rd LOC I/O for 12 Months | F20: =C8 -> 368118.62
B21: =E21 -> RE | C21: =I8 -> 72410.388 | E21: =H2 -> RE | F21: =I8 -> 72410.388
B22: =E22 -> Seller Fin | C22: =F8 -> 226454.8 | E22: =E2 -> Seller Fin | F22: =F8 -> 226454.8
B23: =E23 -> 5th 3rd LOC/Loan | C23: =L8 -> 180341.54 | E23: =K2 -> 5th 3rd LOC/Loan | F23: =L8 -> 180341.54
B24: Annual I/O Period Out Total Debt Service | C24: =SUM(C20:C23) -> 629206.73 | E24: Annual Termed Out Total Debt Service | F24: =SUM(F20:F23) -> 847325.35
B25: Monthly I/O Period Out Total Debt Service | C25: =C24/12 -> 52433.894 | E25: Monthly Termed Out Total Debt Service | F25: =F24/12 -> 70610.446

Sheet Buckeye P&L
B2: Line Item | C2: 2019 | E2: 2020 | G2: 2021 | I2: 2022 | K2: 2023 | M2: 2024 | O2: 2025 YTD
B3: Revenue | C3: 3500693 | E3: 761769 | G3: =1872696 -> 1872696 | I3: 2953728 | K3: 3314500 | M3: 3530489 | O3: =2704628 -> 2704628
B4: COGS | C4: 1384314 | E4: 312564 | G4: 615758 | I4: 1095888 | K4: 1172675 | M4: 1221945 | O4: =864814 -> 864814
B5: Gross Profit | C5: =C3-C4 -> 2116379 | D5: =C5/C3 -> 0.60456001 | E5: =E3-E4 -> 449205 | F5: =E5/E3 -> 0.58968664 | G5: =G3-G4 -> 1256938 | H5: =G5/G3 -> 0.67119169 | I5: =I3-I4 -> 1857840 | J5: =I5/I3 -> 0.62898141 | K5: =K3-K4 -> 2141825 | L5: =K5/K3 -> 0.64619852 | M5: =M3-M4 -> 2308544 | N5: =M5/M3 -> 0.65388789 | O5: =O3-O4 -> 1839814 | P5: =O5/O3 -> 0.6802466
B6: Expenses | C6: 1660864 | D6: =C6/C3 -> 0.47443863 | E6: 463046 | F6: =E6/E3 -> 0.60785619 | G6: 540143 | H6: =G6/G3 -> 0.28843069 | I6: 1090632 | J6: =I6/I3 -> 0.36923914 | K6: 1231856 | L6: =K6/K3 -> 0.37165666 | M6: 1161656 | N6: =M6/M3 -> 0.32903544 | O6: 979854 | P6: =O6/O3 -> 0.3622879
B7: Net Profit | C7: =C5-C6 -> 455515 | D7: =C7/C3 -> 0.13012138 | E7: =E5-E6 -> -13841 | F7: =E7/E3 -> -0.01816955 | G7: =G5-G6 -> 716795 | H7: =G7/G3 -> 0.382761 | I7: =I5-I6 -> 767208 | J7: =I7/I3 -> 0.25974226 | K7: =K5-K6 -> 909969 | L7: =K7/K3 -> 0.27454186 | M7: =M5-M6 -> 1146888 | N7: =M7/M3 -> 0.32485245 | O7: =O5-O6 -> 859960 | P7: =O7/O3 -> 0.3179587
B8: Owner Comp | C8: =109000 -> 109000 | E8: =36333 -> 36333 | G8: =49958 -> 49958 | I8: 115358 | K8: 130800 | M8: 187467 | O8: =339141 -> 339141
B9: Interest | C9: 29436 | E9: 13076 | G9: 11480.83 | I9: 10243 | K9: 7147 | M9: 287 | O9: 29625
B10: Dep + Amort | C10: 662899 | E10: 19469 | G10: 10000 | I10: 0 | K10: 4000 | M10: 0 | O10: 0
B11: EBIDA | C11: =C7+C8+C9+C10 -> 1256850 | D11: =C11/C3 -> 0.35902891 | E11: =E7+E8+E9+E10 -> 55037 | F11: =E11/E3 -> 0.072248936 | G11: =G7+G8+G9+G10 -> 788233.83 | H11: =G11/G3 -> 0.42090859 | I11: =I7+I8+I9+I10 -> 892809 | J11: =I11/I3 -> 0.30226514 | K11: =K7+K8+K9+K10 -> 1051916 | L11: =K11/K3 -> 0.31736793 | M11: =M7+M8+M9+M10 -> 1334642 | N11: =M11/M3 -> 0.37803318 | O11: =O7+O8+O9+O10 -> 1228726 | P11: =O11/O3 -> 0.45430499
K15: 5000000 | M15: =K15/M11 -> 3.746323
K16: 5200000 | M16: =K16/M11 -> 3.8961759
K17: =K16/M11 -> 3.8961759

Sheet Inputs
I2: Year 1 | J2: Year 2 | K2: Year 3 | L2: Year 4 | M2: Year 5
C4: Rate
B5: OG 5th 3rd LOC I/O for 12 Months | C5: 0.075 | D5: 2000000 | E5: Appraised RE Value | F5: LTV | H5: =B5 -> OG 5th 3rd LOC I/O for 12 Months | I5: =12500*12 -> 150000 | J5: =30677*12 -> 368124 | K5: =30677*12 -> 368124 | L5: =30677*12 -> 368124 | M5: =30677*12 -> 368124
B6: RE | C6: 0.068 | D6: =E6*F6 -> 790500 | E6: =930000 -> 930000 | F6: 0.85 | H6: =B6 -> RE | I6: ='Per Loan'!I8 -> 72410.388 | J6: =I6 -> 72410.388 | K6: =J6 -> 72410.388 | L6: =K6 -> 72410.388 | M6: =L6 -> 72410.388
B7: Seller Fin | C7: 0.05 | D7: 1000000 | H7: =B7 -> Seller Fin | I7: ='Per Loan'!$F$8 -> 226454.8 | J7: =I7 -> 226454.8 | K7: =J7 -> 226454.8 | L7: =K7 -> 226454.8 | M7: =L7 -> 226454.8
B8: 5th 3rd LOC/Loan | C8: =C5 -> 0.075 | D8: 750000 | H8: =B8 -> 5th 3rd LOC/Loan | I8: ='Per Loan'!$L$8 -> 180341.54 | J8: ='Per Loan'!$L$8 -> 180341.54 | K8: ='Per Loan'!$L$8 -> 180341.54 | L8: ='Per Loan'!$L$8 -> 180341.54 | M8: ='Per Loan'!$L$8 -> 180341.54
H9: Debt Service | I9: =SUM(I5:I8) -> 629206.73 | J9: =SUM(J5:J8) -> 847330.73 | K9: =SUM(K5:K8) -> 847330.73 | L9: =SUM(L5:L8) -> 847330.73 | M9: =SUM(M5:M8) -> 847330.73
D10: Total Purchase Price | E10: Total RE Price | F10: Operating Business Price | H10: EBITDA @ 3% Growth | I10: 1430000 | J10: =I10*1.03 -> 1472900 | K10: =J10*1.03 -> 1517087 | L10: =K10*1.03 -> 1562599.6 | M10: =L10*1.03 -> 1609477.6
D11: 5000000 | E11: 900000 | F11: =D11-E11 -> 4100000 | H11: Net Cash Flow | I11: =I10-I9 -> 800793.27 | J11: =J10-J9 -> 625569.27 | K11: =K10-K9 -> 669756.27 | L11: =L10-L9 -> 715268.88 | M11: =M10-M9 -> 762146.87
B12: Weighted Rate | H12: DSC | I12: =I10/I9 -> 2.272703 | J12: =J10/J9 -> 1.7382823 | K12: =K10/K9 -> 1.7904308 | L12: =L10/L9 -> 1.8441437 | M12: =M10/M9 -> 1.899468
B13: =(F13/F21)*C5 -> 0.033036009 | C13: OG 5th 3rd LOC | F13: =D5 -> 2000000 | H13: ROI | I13: =I11/$F$19 -> 1.7427492 | J13: =(J11+I11)/$F$19 -> 3.1041622 | K13: =(I11+K11+J11)/$F$19 -> 4.5617384 | L13: =(I11+J11+L11+K11)/$F$19 -> 6.1183628 | M13: =(I11+J11+K11+M11+L11)/$F$19 -> 7.7770067
B14: =(E14/F21)*C6 -> 0.011838784 | C14: RE Loan | E14: =E6*F6 -> 790500 | I14: =((F19/D11)*I23)+((F21/D11)*B21*(1-B22)) -> 0.062765632 | J14: =((F19/D11)*I23)+((F21/D11)*B21*(1-B22)) -> 0.062765632 | K14: =((F19/D11)*I23)+((F21/D11)*B21*(1-B22)) -> 0.062765632 | L14: =((F19/D11)*I23)+((F21/D11)*B21*(1-B22)) -> 0.062765632 | M14: =((F19/D11)*I23)+((F21/D11)*B21*(1-B22)) -> 0.062765632
B15: =(F15/F21)*C7 -> 0.011012003 | C15: Seller Fin | F15: =D7 -> 1000000
B16: =(F16/F21)*C8 -> 0.012388503 | C16: =B8 -> 5th 3rd LOC/Loan | F16: =D8 -> 750000
E17: =E11-E14 -> 109500 | F17: =F11-F13-F15-F16 -> 350000
E19: Cash To Closing | F19: =F17+E17 -> 459500
B21: =SUM(B13:B16) -> 0.0682753 | E21: Total Amount Financed | F21: =F13+E14+F15+F16 -> 4540500 | H21: Equity | I21: =F19/D11 -> 0.0919 | K21: 5400000
A22: Tax-Rate | B22: 0.21 | H22: Debt | I22: =F21/D11 -> 0.9081 | K22: =I10/K21 -> 0.26481481
A23: After Tax RD | B23: =B21*(1-B22) -> 0.053937487 | H23: Cost of Equity | I23: 0.15
F26: =((1256000/5200000)*0.15)+((3944000/5200000)*0.0663*(1-0.21)) -> 0.075956709
D30: =84/12 -> 7 | F30: =F21+F19 -> 5000000
C37: =75-20 -> 55
